pytest_servers/__init__.py
pytest_servers/azure.py
pytest_servers/exceptions.py
pytest_servers/factory.py
pytest_servers/fixtures.py
pytest_servers/gcs.py
pytest_servers/local.py
pytest_servers/py.typed
pytest_servers/s3.py
pytest_servers/utils.py
pytest_servers-0.5.13.dist-info/licenses/LICENSE
pytest_servers-0.5.13.dist-info/METADATA
pytest_servers-0.5.13.dist-info/WHEEL
pytest_servers-0.5.13.dist-info/entry_points.txt
pytest_servers-0.5.13.dist-info/top_level.txt
pytest_servers-0.5.13.dist-info/RECORD
