Metadata-Version: 2.4
Name: pytest-servers
Version: 0.5.13
Summary: pytest servers
Author-email: Iterative <support@dvc.org>
License: Apache-2.0
Project-URL: Issues, https://github.com/iterative/pytest-servers/issues
Project-URL: Source, https://github.com/iterative/pytest-servers
Classifier: Programming Language :: Python :: 3
Classifier: Programming Language :: Python :: 3.9
Classifier: Programming Language :: Python :: 3.10
Classifier: Programming Language :: Python :: 3.11
Classifier: Programming Language :: Python :: 3.12
Classifier: Programming Language :: Python :: 3.13
Classifier: Development Status :: 3 - Alpha
Classifier: Framework :: Pytest
Classifier: Intended Audience :: Developers
Requires-Python: >=3.9
License-File: LICENSE
Requires-Dist: pytest>=6.2
Requires-Dist: requests
Requires-Dist: fsspec
Requires-Dist: universal-pathlib>=0.2.0
Requires-Dist: filelock>=3.3.2
Provides-Extra: docker
Requires-Dist: docker>6; extra == "docker"
Provides-Extra: s3
Requires-Dist: moto[server]>=4; extra == "s3"
Requires-Dist: s3fs[boto3]>=2022.02.0; extra == "s3"
Requires-Dist: botocore>=1.31.17; extra == "s3"
Requires-Dist: PyYAML>=6.0.2; extra == "s3"
Provides-Extra: azure
Requires-Dist: adlfs>=2022.02.22; extra == "azure"
Requires-Dist: pytest-servers[docker]; extra == "azure"
Provides-Extra: gcs
Requires-Dist: gcsfs>=2022.02.22; extra == "gcs"
Requires-Dist: pytest-servers[docker]; extra == "gcs"
Provides-Extra: all
Requires-Dist: pytest-servers[azure,gcs,s3]; extra == "all"
Provides-Extra: tests
Requires-Dist: coverage-enable-subprocess; extra == "tests"
Requires-Dist: coverage[toml]>6; extra == "tests"
Requires-Dist: pytest-sugar==1.1.1; extra == "tests"
Requires-Dist: pytest-xdist==3.8.0; extra == "tests"
Requires-Dist: mypy==1.19.1; extra == "tests"
Requires-Dist: types-requests; extra == "tests"
Provides-Extra: dev
Requires-Dist: pytest-servers[all]; extra == "dev"
Requires-Dist: pytest-servers[tests]; extra == "dev"
Dynamic: license-file
